tapioca_sectigo_api_ssl/__init__.py
tapioca_sectigo_api_ssl/resource_mapping.py
tapioca_sectigo_api_ssl/tapioca_sectigo_api_ssl.py
tapioca_sectigo_api_ssl-0.5.dist-info/DESCRIPTION.rst
tapioca_sectigo_api_ssl-0.5.dist-info/METADATA
tapioca_sectigo_api_ssl-0.5.dist-info/RECORD
tapioca_sectigo_api_ssl-0.5.dist-info/WHEEL
tapioca_sectigo_api_ssl-0.5.dist-info/metadata.json
tapioca_sectigo_api_ssl-0.5.dist-info/top_level.txt
