Metadata-Version: 2.0
Name: tapioca-sectigo-api-ssl
Version: 0.5
Summary: sectigo_api_ssl API wrapper using tapioca
Home-page: https://github.com/Smogin/tapioca-sectigo_api_ssl
Author: Site Blindado S.A.
Author-email: dev@siteblindado.com.br
License: MIT
Keywords: sectigo_api_ssl
Platform: UNKNOWN
Classifier: Development Status :: 5 - Production/Stable
Classifier: Intended Audience :: Developers
Classifier: License :: OSI Approved :: MIT License
Classifier: Natural Language :: English
Classifier: Programming Language :: Python :: 2
Classifier: Programming Language :: Python :: 2.7
Classifier: Programming Language :: Python :: 3
Classifier: Programming Language :: Python :: 3.1
Classifier: Programming Language :: Python :: 3.2
Classifier: Programming Language :: Python :: 3.3
Classifier: Programming Language :: Python :: 3.4
Classifier: Programming Language :: Python :: 3.5
Classifier: Programming Language :: Python :: 3.6
Classifier: Programming Language :: Python :: 3.7
Requires-Dist: tapioca-wrapper (<2)
